{
    "info": {
        "id": 3,
        "name": "Giblin Eunson"
    },
    "levels": {
        "1": {
            "filename": "giblin_eunson_01.png",
            "order": ""
        },
        "G": {
            "filename": "giblin_eunson_g.png",
            "order": ""
        },
        "UG": {
            "filename": "giblin_eunson_ug.png",
            "order": ""
        }
    },
    "resources": {
        "GE-1-01": {
            "level": "1",
            "x": 1476.2239990234375,
            "y": 499.41766357421875
        },
        "GE-1-02": {
            "level": "1",
            "x": 1476.5811767578125,
            "y": 456.5561218261719
        },
        "GE-1-03": {
            "level": "1",
            "x": 1186.756591796875,
            "y": 724.6643676757812
        },
        "GE-1-04": {
            "level": "1",
            "x": 1188.0198974609375,
            "y": 685.0804443359375
        },
        "GE-1-05": {
            "level": "1",
            "x": 1187.598876953125,
            "y": 645.49658203125
        },
        "GE-1-06": {
            "level": "1",
            "x": 937.6712646484375,
            "y": 13.266206741333008
        },
        "GE-G-01": {
            "level": "G",
            "x": 802.2926025390625,
            "y": 499.33740234375
        },
        "GE-G-02": {
            "level": "G",
            "x": 803.3014526367188,
            "y": 543.5342407226562
        },
        "GE-G-03": {
            "level": "G",
            "x": 803.2045288085938,
            "y": 588.1752319335938
        },
        "GE-G-04": {
            "level": "G",
            "x": 1094.259521484375,
            "y": 586.0380249023438
        },
        "GE-G-05": {
            "level": "G",
            "x": 1095.585205078125,
            "y": 541.3633422851562
        },
        "GE-G-06": {
            "level": "G",
            "x": 1094.4810791015625,
            "y": 495.36077880859375
        },
        "GE-G-07": {
            "level": "G",
            "x": 1094.1131591796875,
            "y": 449.3581848144531
        },
        "GE-G-08": {
            "level": "G",
            "x": 1472.438232421875,
            "y": 450.09417724609375
        },
        "GE-G-09": {
            "level": "G",
            "x": 1472.438232421875,
            "y": 496.4647521972656
        },
        "GE-G-10": {
            "level": "G",
            "x": 1471.7022705078125,
            "y": 540.9952392578125
        },
        "GE-G-11": {
            "level": "G",
            "x": 1472.8062744140625,
            "y": 585.893798828125
        },
        "GE-G-12": {
            "level": "G",
            "x": 1632.1593017578125,
            "y": 482.8480224609375
        },
        "GE-G-13": {
            "level": "G",
            "x": 1590.572998046875,
            "y": 502.3531188964844
        },
        "GE-G-14": {
            "level": "G",
            "x": 1590.572998046875,
            "y": 547.9876708984375
        },
        "GE-G-15": {
            "level": "G",
            "x": 1633.263427734375,
            "y": 567.4927368164062
        },
        "GE-G-16": {
            "level": "G",
            "x": 1677.4259033203125,
            "y": 549.8277587890625
        },
        "GE-G-17": {
            "level": "G",
            "x": 1677.7939453125,
            "y": 503.0891418457031
        },
        "GE-UG-01": {
            "level": "UG",
            "x": 291.9329528808594,
            "y": 820.6414184570312
        },
        "GE-UG-02": {
            "level": "UG",
            "x": 291.7662048339844,
            "y": 871.3197021484375
        },
        "GE-UG-03": {
            "level": "UG",
            "x": 291.7662048339844,
            "y": 920.8311157226562
        },
        "GE-UG-04": {
            "level": "UG",
            "x": 441.80072021484375,
            "y": 919.99755859375
        },
        "GE-UG-05": {
            "level": "UG",
            "x": 441.9674072265625,
            "y": 870.4862060546875
        },
        "GE-UG-06": {
            "level": "UG",
            "x": 441.80072021484375,
            "y": 820.8080444335938
        },
        "GE-UG-07": {
            "level": "UG",
            "x": 561.328125,
            "y": 920.49755859375
        },
        "GE-UG-08": {
            "level": "UG",
            "x": 561.328125,
            "y": 870.6527709960938
        },
        "GE-UG-09": {
            "level": "UG",
            "x": 561.9949340820312,
            "y": 820.8079833984375
        },
        "GE-UG-10": {
            "level": "UG",
            "x": 593.8356323242188,
            "y": 820.9747314453125
        },
        "GE-UG-11": {
            "level": "UG",
            "x": 593.6688842773438,
            "y": 871.486328125
        },
        "GE-UG-12": {
            "level": "UG",
            "x": 593.6688842773438,
            "y": 920.49755859375
        },
        "GE-UG-15": {
            "level": "UG",
            "x": 857.7167358398438,
            "y": 920.0205688476562
        },
        "GE-UG-16": {
            "level": "UG",
            "x": 857.677490234375,
            "y": 870.3668823242188
        },
        "GE-UG-17": {
            "level": "UG",
            "x": 858.5634765625,
            "y": 820.4564819335938
        },
        "GE-UG-18": {
            "level": "UG",
            "x": 1010.3621215820312,
            "y": 821.047119140625
        },
        "GE-UG-19": {
            "level": "UG",
            "x": 1009.771484375,
            "y": 870.6622314453125
        },
        "GE-UG-20": {
            "level": "UG",
            "x": 1010.3621215820312,
            "y": 920.5726928710938
        },
        "GE-UG-22": {
            "level": "UG",
            "x": 1165.8460693359375,
            "y": 147.20550537109375
        },
        "GE-UG-23": {
            "level": "UG",
            "x": 688.4750366210938,
            "y": 638.53515625
        },
        "GE-UG-25": {
            "level": "UG",
            "x": 688.4750366210938,
            "y": 599.2957763671875
        },
        "GE-UG-27": {
            "level": "UG",
            "x": 650.8052368164062,
            "y": 557.4404907226562
        },
        "GE-UG-28": {
            "level": "UG",
            "x": 607.9035034179688,
            "y": 557.9636840820312
        },
        "GE-UG-29": {
            "level": "UG",
            "x": 100.29827117919922,
            "y": 709.1666259765625
        },
        "GE-UG-30": {
            "level": "UG",
            "x": 61.55828857421875,
            "y": 44.68104553222656
        },
        "GE-UG-31": {
            "level": "UG",
            "x": 22.250125885009766,
            "y": 45.46720504760742
        },
        "Project Room 1": {
            "level": "G",
            "x": 1205.691162109375,
            "y": 233.73199462890625
        },
        "Project Room 10": {
            "level": "1",
            "x": 66.7712173461914,
            "y": 313.842041015625
        },
        "Project Room 2": {
            "level": "G",
            "x": 1344.06689453125,
            "y": 233.73199462890625
        },
        "Project Room 3": {
            "level": "G",
            "x": 1344.14013671875,
            "y": 64.39275360107422
        },
        "Project Room 4": {
            "level": "G",
            "x": 1205.0283203125,
            "y": 95.30648803710938
        },
        "Project Room 5": {
            "level": "UG",
            "x": 1327.9439697265625,
            "y": 277.82940673828125
        },
        "Project Room 6": {
            "level": "UG",
            "x": 1322.0533447265625,
            "y": 166.09808349609375
        },
        "Project Room 8": {
            "level": "1",
            "x": 1788.9222412109375,
            "y": 436.2473449707031
        },
        "Project Room 9": {
            "level": "1",
            "x": 1789.42626953125,
            "y": 339.5577697753906
        }
    }
}
